[
	{
		"worldId": "custom_DesignStuff_00092",
		"containerTpl": "578f87a3245977356274f2cb"
	},
	{
		"worldId": "custom_DesignStuff_00059",
		"containerTpl": "5909d7cf86f77470ee57d75a"
	},
	{
		"worldId": "custom_DesignStuff_00091",
		"containerTpl": "578f87a3245977356274f2cb"
	},
	{
		"worldId": "custom_DesignStuff_00079",
		"containerTpl": "578f8778245977358849a9b5"
	},
	{
		"worldId": "custom_DesignStuff_00069",
		"containerTpl": "5909d89086f77472591234a0"
	},
	{
		"worldId": "custom_DesignStuff_00072",
		"containerTpl": "5909d76c86f77471e53d2adf"
	},
	{
		"worldId": "custom_DesignStuff_00065",
		"containerTpl": "5909d5ef86f77467974efbd8"
	},
	{
		"worldId": "custom_DesignStuff_00101",
		"containerTpl": "5d6d2bb386f774785b07a77a"
	},
	{
		"worldId": "custom_DesignStuff_00083",
		"containerTpl": "5d6fd45b86f774317075ed43"
	},
	{
		"worldId": "custom_DesignStuff_00035",
		"containerTpl": "5909d76c86f77471e53d2adf"
	},
	{
		"worldId": "custom_DesignStuff_00096",
		"containerTpl": "5d6d2bb386f774785b07a77a"
	},
	{
		"worldId": "custom_DesignStuff_00050",
		"containerTpl": "5909d76c86f77471e53d2adf"
	},
	{
		"worldId": "custom_DesignStuff_00051",
		"containerTpl": "5909d7cf86f77470ee57d75a"
	},
	{
		"worldId": "custom_DesignStuff_00046",
		"containerTpl": "5909d50c86f774659e6aaebe"
	},
	{
		"worldId": "custom_DesignStuff_00052",
		"containerTpl": "5909d5ef86f77467974efbd8"
	},
	{
		"worldId": "custom_DesignStuff_00047",
		"containerTpl": "5909d4c186f7746ad34e805a"
	},
	{
		"worldId": "custom_DesignStuff_00070",
		"containerTpl": "5909d7cf86f77470ee57d75a"
	},
	{
		"worldId": "custom_DesignStuff_00103",
		"containerTpl": "5d6d2bb386f774785b07a77a"
	},
	{
		"worldId": "custom_DesignStuff_00087",
		"containerTpl": "578f87a3245977356274f2cb"
	},
	{
		"worldId": "custom_DesignStuff_00093",
		"containerTpl": "578f87a3245977356274f2cb"
	},
	{
		"worldId": "custom_DesignStuff_00095",
		"containerTpl": "5d6d2b5486f774785c2ba8ea"
	},
	{
		"worldId": "custom_DesignStuff_00053",
		"containerTpl": "5909d7cf86f77470ee57d75a"
	},
	{
		"worldId": "custom_DesignStuff_00058",
		"containerTpl": "5909d7cf86f77470ee57d75a"
	},
	{
		"worldId": "custom_DesignStuff_00043",
		"containerTpl": "5909d7cf86f77470ee57d75a"
	},
	{
		"worldId": "custom_DesignStuff_00066",
		"containerTpl": "5909d5ef86f77467974efbd8"
	},
	{
		"worldId": "custom_DesignStuff_00049",
		"containerTpl": "5909d50c86f774659e6aaebe"
	},
	{
		"worldId": "custom_DesignStuff_00086",
		"containerTpl": "578f87a3245977356274f2cb"
	},
	{
		"worldId": "custom_DesignStuff_00074",
		"containerTpl": "578f87ad245977356274f2cc"
	},
	{
		"worldId": "custom_DesignStuff_00056",
		"containerTpl": "5909d7cf86f77470ee57d75a"
	},
	{
		"worldId": "custom_DesignStuff_00062",
		"containerTpl": "5909d4c186f7746ad34e805a"
	},
	{
		"worldId": "custom_DesignStuff_00057",
		"containerTpl": "5909d5ef86f77467974efbd8"
	},
	{
		"worldId": "custom_DesignStuff_00038",
		"containerTpl": "5909d7cf86f77470ee57d75a"
	},
	{
		"worldId": "custom_DesignStuff_00068",
		"containerTpl": "5909d4c186f7746ad34e805a"
	},
	{
		"worldId": "custom_DesignStuff_00108",
		"containerTpl": "5d6d2b5486f774785c2ba8ea"
	},
	{
		"worldId": "custom_DesignStuff_00044",
		"containerTpl": "5909d5ef86f77467974efbd8"
	},
	{
		"worldId": "custom_DesignStuff_00099",
		"containerTpl": "5d6d2bb386f774785b07a77a"
	},
	{
		"worldId": "custom_DesignStuff_00080",
		"containerTpl": "5909d50c86f774659e6aaebe"
	},
	{
		"worldId": "custom_DesignStuff_00048",
		"containerTpl": "5909d50c86f774659e6aaebe"
	},
	{
		"worldId": "custom_DesignStuff_00060",
		"containerTpl": "5909d76c86f77471e53d2adf"
	},
	{
		"worldId": "custom_DesignStuff_00106",
		"containerTpl": "5d6d2b5486f774785c2ba8ea"
	},
	{
		"worldId": "custom_DesignStuff_00037",
		"containerTpl": "5909d5ef86f77467974efbd8"
	},
	{
		"worldId": "custom_DesignStuff_00104",
		"containerTpl": "5d6d2b5486f774785c2ba8ea"
	},
	{
		"worldId": "custom_DesignStuff_00105",
		"containerTpl": "5d6d2bb386f774785b07a77a"
	},
	{
		"worldId": "custom_DesignStuff_00040",
		"containerTpl": "5909d7cf86f77470ee57d75a"
	},
	{
		"worldId": "custom_DesignStuff_00085",
		"containerTpl": "578f87a3245977356274f2cb"
	},
	{
		"worldId": "custom_DesignStuff_00064",
		"containerTpl": "5909d50c86f774659e6aaebe"
	},
	{
		"worldId": "custom_DesignStuff_00073",
		"containerTpl": "5909d4c186f7746ad34e805a"
	},
	{
		"worldId": "custom_DesignStuff_00113",
		"containerTpl": "5d6d2bb386f774785b07a77a"
	},
	{
		"worldId": "custom_DesignStuff_00045",
		"containerTpl": "5909d7cf86f77470ee57d75a"
	},
	{
		"worldId": "custom_DesignStuff_00063",
		"containerTpl": "5909d4c186f7746ad34e805a"
	},
	{
		"worldId": "custom_DesignStuff_00107",
		"containerTpl": "5d6d2b5486f774785c2ba8ea"
	},
	{
		"worldId": "custom_DesignStuff_00067",
		"containerTpl": "5909d7cf86f77470ee57d75a"
	},
	{
		"worldId": "custom_DesignStuff_00077",
		"containerTpl": "5909d5ef86f77467974efbd8"
	},
	{
		"worldId": "custom_DesignStuff_00094",
		"containerTpl": "5d6d2bb386f774785b07a77a"
	},
	{
		"worldId": "custom_DesignStuff_00090",
		"containerTpl": "578f87a3245977356274f2cb"
	},
	{
		"worldId": "custom_DesignStuff_00061",
		"containerTpl": "5909d5ef86f77467974efbd8"
	},
	{
		"worldId": "custom_DesignStuff_00081",
		"containerTpl": "578f87ad245977356274f2cc"
	},
	{
		"worldId": "custom_DesignStuff_00088",
		"containerTpl": "578f87a3245977356274f2cb"
	},
	{
		"worldId": "custom_DesignStuff_00098",
		"containerTpl": "5d6d2bb386f774785b07a77a"
	},
	{
		"worldId": "custom_DesignStuff_00055",
		"containerTpl": "5909d4c186f7746ad34e805a"
	},
	{
		"worldId": "custom_DesignStuff_00039",
		"containerTpl": "5909d7cf86f77470ee57d75a"
	},
	{
		"worldId": "custom_DesignStuff_00115",
		"containerTpl": "5d6d2b5486f774785c2ba8ea"
	},
	{
		"worldId": "custom_DesignStuff_00036",
		"containerTpl": "5909d7cf86f77470ee57d75a"
	},
	{
		"worldId": "custom_DesignStuff_00110",
		"containerTpl": "5d6d2bb386f774785b07a77a"
	},
	{
		"worldId": "custom_DesignStuff_00041",
		"containerTpl": "5909d76c86f77471e53d2adf"
	},
	{
		"worldId": "custom_DesignStuff_00082",
		"containerTpl": "5909d50c86f774659e6aaebe"
	},
	{
		"worldId": "custom_DesignStuff_00112",
		"containerTpl": "5d6d2bb386f774785b07a77a"
	},
	{
		"worldId": "custom_DesignStuff_00075",
		"containerTpl": "5909d7cf86f77470ee57d75a"
	},
	{
		"worldId": "custom_DesignStuff_00100",
		"containerTpl": "5d6d2b5486f774785c2ba8ea"
	},
	{
		"worldId": "custom_DesignStuff_00042",
		"containerTpl": "5909d5ef86f77467974efbd8"
	},
	{
		"worldId": "custom_DesignStuff_00071",
		"containerTpl": "5909d50c86f774659e6aaebe"
	},
	{
		"worldId": "custom_DesignStuff_00089",
		"containerTpl": "578f87a3245977356274f2cb"
	},
	{
		"worldId": "custom_DesignStuff_00102",
		"containerTpl": "5d6d2b5486f774785c2ba8ea"
	},
	{
		"worldId": "custom_DesignStuff_00084",
		"containerTpl": "5909d36d86f774660f0bb900"
	},
	{
		"worldId": "custom_DesignStuff_00054",
		"containerTpl": "5909d5ef86f77467974efbd8"
	},
	{
		"worldId": "custom_DesignStuff_00109",
		"containerTpl": "5d6d2bb386f774785b07a77a"
	},
	{
		"worldId": "custom_DesignStuff_00114",
		"containerTpl": "5d6d2bb386f774785b07a77a"
	},
	{
		"worldId": "custom_DesignStuff_00097",
		"containerTpl": "5d6d2bb386f774785b07a77a"
	},
	{
		"worldId": "custom_DesignStuff_00076",
		"containerTpl": "578f87ad245977356274f2cc"
	},
	{
		"worldId": "custom_DesignStuff_00078",
		"containerTpl": "578f8778245977358849a9b5"
	},
	{
		"worldId": "custom_DesignStuff_00116",
		"containerTpl": "5d6d2bb386f774785b07a77a"
	},
	{
		"worldId": "custom_DesignStuff_00111",
		"containerTpl": "5d6d2b5486f774785c2ba8ea"
	},
	{
		"worldId": "custom_Garage_00024",
		"containerTpl": "578f87ad245977356274f2cc"
	},
	{
		"worldId": "custom_Garage_00022",
		"containerTpl": "578f87a3245977356274f2cb"
	},
	{
		"worldId": "custom_Garage_00019",
		"containerTpl": "578f8778245977358849a9b5"
	},
	{
		"worldId": "custom_Garage_00021",
		"containerTpl": "5909e4b686f7747f5b744fa4"
	},
	{
		"worldId": "custom_Garage_00020",
		"containerTpl": "578f87a3245977356274f2cb"
	},
	{
		"worldId": "custom_Garage_00023",
		"containerTpl": "5909d24f86f77466f56e6855"
	},
	{
		"worldId": "custom_Garage_00018",
		"containerTpl": "578f8778245977358849a9b5"
	},
	{
		"worldId": "custom_Garage_00025",
		"containerTpl": "578f87ad245977356274f2cc"
	},
	{
		"worldId": "custom_Tamozhnya_00006",
		"containerTpl": "578f8782245977354405a1e3"
	},
	{
		"worldId": "custom_Tamozhnya_00019",
		"containerTpl": "578f87b7245977356274f2cd"
	},
	{
		"worldId": "custom_Tamozhnya_00018",
		"containerTpl": "578f87b7245977356274f2cd"
	},
	{
		"worldId": "custom_Tamozhnya_00017",
		"containerTpl": "578f87b7245977356274f2cd"
	},
	{
		"worldId": "custom_Tamozhnya_00016",
		"containerTpl": "578f87b7245977356274f2cd"
	},
	{
		"worldId": "custom_Tamozhnya_00007",
		"containerTpl": "59139c2186f77411564f8e42"
	},
	{
		"worldId": "custom_Tamozhnya_00024",
		"containerTpl": "578f87b7245977356274f2cd"
	},
	{
		"worldId": "custom_Tamozhnya_00023",
		"containerTpl": "578f87b7245977356274f2cd"
	},
	{
		"worldId": "custom_Tamozhnya_00022",
		"containerTpl": "578f87b7245977356274f2cd"
	},
	{
		"worldId": "custom_Tamozhnya_00021",
		"containerTpl": "578f87b7245977356274f2cd"
	},
	{
		"worldId": "custom_Tamozhnya_00014",
		"containerTpl": "578f8778245977358849a9b5"
	},
	{
		"worldId": "custom_Tamozhnya_00009",
		"containerTpl": "59139c2186f77411564f8e42"
	},
	{
		"worldId": "custom_Tamozhnya_00025",
		"containerTpl": "578f87ad245977356274f2cc"
	},
	{
		"worldId": "custom_Tamozhnya_00008",
		"containerTpl": "59139c2186f77411564f8e42"
	},
	{
		"worldId": "custom_Tamozhnya_00010",
		"containerTpl": "578f87a3245977356274f2cb"
	},
	{
		"worldId": "custom_Tamozhnya_00015",
		"containerTpl": "578f8778245977358849a9b5"
	},
	{
		"worldId": "custom_Tamozhnya_00012",
		"containerTpl": "578f87ad245977356274f2cc"
	},
	{
		"worldId": "custom_Tamozhnya_00011",
		"containerTpl": "578f8778245977358849a9b5"
	},
	{
		"worldId": "custom_Tamozhnya_00020",
		"containerTpl": "578f87a3245977356274f2cb"
	},
	{
		"worldId": "custom_Tamozhnya_00013",
		"containerTpl": "578f87a3245977356274f2cb"
	},
	{
		"worldId": "custom_TrailerPark_00019",
		"containerTpl": "578f8778245977358849a9b5"
	},
	{
		"worldId": "custom_TrailerPark_00018",
		"containerTpl": "578f8778245977358849a9b5"
	},
	{
		"worldId": "custom_TrailerPark_00021",
		"containerTpl": "578f87a3245977356274f2cb"
	},
	{
		"worldId": "custom_TrailerPark_00020",
		"containerTpl": "578f8778245977358849a9b5"
	},
	{
		"worldId": "custom_factoryStorageZone_00023",
		"containerTpl": "5914944186f774189e5e76c2"
	},
	{
		"worldId": "custom_factoryStorageZone_00021",
		"containerTpl": "578f87ad245977356274f2cc"
	},
	{
		"worldId": "custom_factoryStorageZone_00020",
		"containerTpl": "578f87b7245977356274f2cd"
	},
	{
		"worldId": "custom_factoryStorageZone_00019",
		"containerTpl": "578f87b7245977356274f2cd"
	},
	{
		"worldId": "custom_factoryStorageZone_00018",
		"containerTpl": "578f87b7245977356274f2cd"
	},
	{
		"worldId": "custom_factoryStorageZone_00017",
		"containerTpl": "578f87b7245977356274f2cd"
	},
	{
		"worldId": "custom_factoryStorageZone_00022",
		"containerTpl": "578f8778245977358849a9b5"
	},
	{
		"worldId": "custom_factoryStorageZone_00016",
		"containerTpl": "578f87ad245977356274f2cc"
	},
	{
		"worldId": "custom_Obshezhitie_00035",
		"containerTpl": "5909d36d86f774660f0bb900"
	},
	{
		"worldId": "custom_Obshezhitie_00034",
		"containerTpl": "578f879c24597735401e6bc6"
	},
	{
		"worldId": "custom_Obshezhitie_1_indoor_00042",
		"containerTpl": "59139c2186f77411564f8e42"
	},
	{
		"worldId": "custom_Obshezhitie_1_indoor_00069",
		"containerTpl": "578f8778245977358849a9b5"
	},
	{
		"worldId": "custom_Obshezhitie_1_indoor_00061",
		"containerTpl": "578f8778245977358849a9b5"
	},
	{
		"worldId": "custom_Obshezhitie_1_indoor_00043",
		"containerTpl": "5909d4c186f7746ad34e805a"
	},
	{
		"worldId": "custom_Obshezhitie_1_indoor_00037",
		"containerTpl": "578f8782245977354405a1e3"
	},
	{
		"worldId": "custom_Obshezhitie_1_indoor_00032",
		"containerTpl": "578f87ad245977356274f2cc"
	},
	{
		"worldId": "custom_Obshezhitie_1_indoor_00033",
		"containerTpl": "578f87a3245977356274f2cb"
	},
	{
		"worldId": "custom_Obshezhitie_1_indoor_00041",
		"containerTpl": "578f8782245977354405a1e3"
	},
	{
		"worldId": "custom_Obshezhitie_1_indoor_00047",
		"containerTpl": "5909d50c86f774659e6aaebe"
	},
	{
		"worldId": "custom_Obshezhitie_1_indoor_00067",
		"containerTpl": "578f87ad245977356274f2cc"
	},
	{
		"worldId": "custom_Obshezhitie_1_indoor_00039",
		"containerTpl": "578f8778245977358849a9b5"
	},
	{
		"worldId": "custom_Obshezhitie_1_indoor_00035",
		"containerTpl": "5909d45286f77465a8136dc6"
	},
	{
		"worldId": "custom_Obshezhitie_1_indoor_00068",
		"containerTpl": "578f8778245977358849a9b5"
	},
	{
		"worldId": "custom_Obshezhitie_1_indoor_00034",
		"containerTpl": "5909d45286f77465a8136dc6"
	},
	{
		"worldId": "custom_Obshezhitie_1_indoor_00059",
		"containerTpl": "578f87a3245977356274f2cb"
	},
	{
		"worldId": "custom_Obshezhitie_1_indoor_00045",
		"containerTpl": "578f8778245977358849a9b5"
	},
	{
		"worldId": "custom_Obshezhitie_1_indoor_00046",
		"containerTpl": "578f8778245977358849a9b5"
	},
	{
		"worldId": "custom_Obshezhitie_1_indoor_00056",
		"containerTpl": "578f87b7245977356274f2cd"
	},
	{
		"worldId": "custom_Obshezhitie_1_indoor_00054",
		"containerTpl": "578f87b7245977356274f2cd"
	},
	{
		"worldId": "custom_Obshezhitie_1_indoor_00053",
		"containerTpl": "578f87b7245977356274f2cd"
	},
	{
		"worldId": "custom_Obshezhitie_1_indoor_00055",
		"containerTpl": "578f87b7245977356274f2cd"
	},
	{
		"worldId": "custom_Obshezhitie_1_indoor_00066",
		"containerTpl": "578f87ad245977356274f2cc"
	},
	{
		"worldId": "custom_Obshezhitie_1_indoor_00057",
		"containerTpl": "578f8778245977358849a9b5"
	},
	{
		"worldId": "custom_Obshezhitie_1_indoor_00058",
		"containerTpl": "578f8778245977358849a9b5"
	},
	{
		"worldId": "custom_Obshezhitie_1_indoor_00036",
		"containerTpl": "5909d76c86f77471e53d2adf"
	},
	{
		"worldId": "custom_Obshezhitie_1_indoor_00060",
		"containerTpl": "578f8778245977358849a9b5"
	},
	{
		"worldId": "custom_Obshezhitie_1_indoor_00048",
		"containerTpl": "5909e4b686f7747f5b744fa4"
	},
	{
		"worldId": "custom_Obshezhitie_1_indoor_00044",
		"containerTpl": "578f8782245977354405a1e3"
	},
	{
		"worldId": "custom_Obshezhitie_1_indoor_00052",
		"containerTpl": "578f87b7245977356274f2cd"
	},
	{
		"worldId": "custom_Obshezhitie_1_indoor_00051",
		"containerTpl": "578f87b7245977356274f2cd"
	},
	{
		"worldId": "custom_Obshezhitie_1_indoor_00049",
		"containerTpl": "578f87b7245977356274f2cd"
	},
	{
		"worldId": "custom_Obshezhitie_1_indoor_00050",
		"containerTpl": "578f87b7245977356274f2cd"
	},
	{
		"worldId": "custom_Obshezhitie_1_indoor_00040",
		"containerTpl": "578f87a3245977356274f2cb"
	},
	{
		"worldId": "custom_Obshezhitie_1_indoor_00038",
		"containerTpl": "578f8778245977358849a9b5"
	},
	{
		"worldId": "custom_Obshezhitie_1_indoor_00064",
		"containerTpl": "578f87b7245977356274f2cd"
	},
	{
		"worldId": "custom_Obshezhitie_1_indoor_00063",
		"containerTpl": "578f87b7245977356274f2cd"
	},
	{
		"worldId": "custom_Obshezhitie_1_indoor_00062",
		"containerTpl": "578f87b7245977356274f2cd"
	},
	{
		"worldId": "custom_Obshezhitie_1_indoor_00065",
		"containerTpl": "578f87b7245977356274f2cd"
	},
	{
		"worldId": "custom_Obshezhitie_2_indoor_00090",
		"containerTpl": "578f87ad245977356274f2cc"
	},
	{
		"worldId": "custom_Obshezhitie_2_indoor_00071",
		"containerTpl": "578f87ad245977356274f2cc"
	},
	{
		"worldId": "custom_Obshezhitie_2_indoor_00082",
		"containerTpl": "578f8778245977358849a9b5"
	},
	{
		"worldId": "custom_Obshezhitie_2_indoor_00084",
		"containerTpl": "578f8778245977358849a9b5"
	},
	{
		"worldId": "custom_Obshezhitie_2_indoor_00069",
		"containerTpl": "578f8778245977358849a9b5"
	},
	{
		"worldId": "custom_Obshezhitie_2_indoor_00086",
		"containerTpl": "578f8778245977358849a9b5"
	},
	{
		"worldId": "custom_Obshezhitie_2_indoor_00060",
		"containerTpl": "59139c2186f77411564f8e42"
	},
	{
		"worldId": "custom_Obshezhitie_2_indoor_00076",
		"containerTpl": "578f87a3245977356274f2cb"
	},
	{
		"worldId": "custom_Obshezhitie_2_indoor_00072",
		"containerTpl": "578f87ad245977356274f2cc"
	},
	{
		"worldId": "custom_Obshezhitie_2_indoor_00089",
		"containerTpl": "578f8778245977358849a9b5"
	},
	{
		"worldId": "custom_Obshezhitie_2_indoor_00059",
		"containerTpl": "578f8778245977358849a9b5"
	},
	{
		"worldId": "custom_Obshezhitie_2_indoor_00087",
		"containerTpl": "578f8778245977358849a9b5"
	},
	{
		"worldId": "custom_Obshezhitie_2_indoor_00088",
		"containerTpl": "578f8778245977358849a9b5"
	},
	{
		"worldId": "custom_Obshezhitie_2_indoor_00064",
		"containerTpl": "578f87b7245977356274f2cd"
	},
	{
		"worldId": "custom_Obshezhitie_2_indoor_00063",
		"containerTpl": "578f87b7245977356274f2cd"
	},
	{
		"worldId": "custom_Obshezhitie_2_indoor_00062",
		"containerTpl": "578f87b7245977356274f2cd"
	},
	{
		"worldId": "custom_Obshezhitie_2_indoor_00061",
		"containerTpl": "578f87b7245977356274f2cd"
	},
	{
		"worldId": "custom_Obshezhitie_2_indoor_00083",
		"containerTpl": "578f87a3245977356274f2cb"
	},
	{
		"worldId": "custom_Obshezhitie_2_indoor_00068",
		"containerTpl": "578f87b7245977356274f2cd"
	},
	{
		"worldId": "custom_Obshezhitie_2_indoor_00067",
		"containerTpl": "578f87b7245977356274f2cd"
	},
	{
		"worldId": "custom_Obshezhitie_2_indoor_00066",
		"containerTpl": "578f87b7245977356274f2cd"
	},
	{
		"worldId": "custom_Obshezhitie_2_indoor_00065",
		"containerTpl": "578f87b7245977356274f2cd"
	},
	{
		"worldId": "custom_Obshezhitie_2_indoor_00055",
		"containerTpl": "578f8778245977358849a9b5"
	},
	{
		"worldId": "custom_Obshezhitie_2_indoor_00054",
		"containerTpl": "578f87b7245977356274f2cd"
	},
	{
		"worldId": "custom_Obshezhitie_2_indoor_00053",
		"containerTpl": "578f87b7245977356274f2cd"
	},
	{
		"worldId": "custom_Obshezhitie_2_indoor_00052",
		"containerTpl": "578f87b7245977356274f2cd"
	},
	{
		"worldId": "custom_Obshezhitie_2_indoor_00051",
		"containerTpl": "578f87b7245977356274f2cd"
	},
	{
		"worldId": "custom_Obshezhitie_2_indoor_00079",
		"containerTpl": "5937ef2b86f77408a47244b3"
	},
	{
		"worldId": "custom_Obshezhitie_2_indoor_00056",
		"containerTpl": "578f8778245977358849a9b5"
	},
	{
		"worldId": "custom_Obshezhitie_2_indoor_00078",
		"containerTpl": "578f8778245977358849a9b5"
	},
	{
		"worldId": "custom_Obshezhitie_2_indoor_00077",
		"containerTpl": "578f8782245977354405a1e3"
	},
	{
		"worldId": "custom_Obshezhitie_2_indoor_00050",
		"containerTpl": "578f87a3245977356274f2cb"
	},
	{
		"worldId": "custom_Obshezhitie_2_indoor_00070",
		"containerTpl": "578f8778245977358849a9b5"
	},
	{
		"worldId": "custom_Obshezhitie_2_indoor_00075",
		"containerTpl": "578f8778245977358849a9b5"
	},
	{
		"worldId": "custom_Obshezhitie_2_indoor_00057",
		"containerTpl": "578f8778245977358849a9b5"
	},
	{
		"worldId": "custom_Obshezhitie_2_indoor_00080",
		"containerTpl": "59139c2186f77411564f8e42"
	},
	{
		"worldId": "custom_Obshezhitie_2_indoor_00081",
		"containerTpl": "578f8782245977354405a1e3"
	},
	{
		"worldId": "custom_Obshezhitie_2_indoor_00085",
		"containerTpl": "578f8778245977358849a9b5"
	},
	{
		"worldId": "custom_Obshezhitie_2_indoor_00058",
		"containerTpl": "578f8778245977358849a9b5"
	},
	{
		"worldId": "custom_Obshezhitie_2_indoor_00074",
		"containerTpl": "578f8778245977358849a9b5"
	},
	{
		"worldId": "custom_Obshezhitie_2_indoor_00073",
		"containerTpl": "578f87ad245977356274f2cc"
	},
	{
		"worldId": "custom_AZS_00047",
		"containerTpl": "578f879c24597735401e6bc6"
	},
	{
		"worldId": "custom_AZS_00045",
		"containerTpl": "5909d4c186f7746ad34e805a"
	},
	{
		"worldId": "custom_AZS_00050",
		"containerTpl": "578f879c24597735401e6bc6"
	},
	{
		"worldId": "custom_AZS_00051",
		"containerTpl": "578f87ad245977356274f2cc"
	},
	{
		"worldId": "custom_AZS_00052",
		"containerTpl": "578f87ad245977356274f2cc"
	},
	{
		"worldId": "custom_AZS_00049",
		"containerTpl": "578f879c24597735401e6bc6"
	},
	{
		"worldId": "custom_AZS_00043",
		"containerTpl": "578f87a3245977356274f2cb"
	},
	{
		"worldId": "custom_AZS_00044",
		"containerTpl": "578f8782245977354405a1e3"
	},
	{
		"worldId": "custom_AZS_00048",
		"containerTpl": "578f879c24597735401e6bc6"
	},
	{
		"worldId": "custom_AZS_00046",
		"containerTpl": "5909d24f86f77466f56e6855"
	},
	{
		"worldId": "custom_mazuto_00043",
		"containerTpl": "5909d50c86f774659e6aaebe"
	},
	{
		"worldId": "custom_mazuto_00029",
		"containerTpl": "578f8778245977358849a9b5"
	},
	{
		"worldId": "custom_mazuto_00041",
		"containerTpl": "578f87ad245977356274f2cc"
	},
	{
		"worldId": "custom_mazuto_00047",
		"containerTpl": "59139c2186f77411564f8e42"
	},
	{
		"worldId": "custom_mazuto_00039",
		"containerTpl": "578f8778245977358849a9b5"
	},
	{
		"worldId": "custom_mazuto_00045",
		"containerTpl": "5909d89086f77472591234a0"
	},
	{
		"worldId": "custom_mazuto_00034",
		"containerTpl": "59139c2186f77411564f8e42"
	},
	{
		"worldId": "custom_mazuto_00040",
		"containerTpl": "5909d7cf86f77470ee57d75a"
	},
	{
		"worldId": "custom_mazuto_00030",
		"containerTpl": "578f8778245977358849a9b5"
	},
	{
		"worldId": "custom_mazuto_00044",
		"containerTpl": "5909d89086f77472591234a0"
	},
	{
		"worldId": "custom_mazuto_00036",
		"containerTpl": "5909d50c86f774659e6aaebe"
	},
	{
		"worldId": "custom_mazuto_00032",
		"containerTpl": "578f8778245977358849a9b5"
	},
	{
		"worldId": "custom_mazuto_00031",
		"containerTpl": "578f87ad245977356274f2cc"
	},
	{
		"worldId": "custom_mazuto_00038",
		"containerTpl": "5909d50c86f774659e6aaebe"
	},
	{
		"worldId": "custom_mazuto_00037",
		"containerTpl": "5909d24f86f77466f56e6855"
	},
	{
		"worldId": "custom_mazuto_00042",
		"containerTpl": "5909e4b686f7747f5b744fa4"
	},
	{
		"worldId": "custom_mazuto_00046",
		"containerTpl": "59139c2186f77411564f8e42"
	},
	{
		"worldId": "custom_mazuto_00033",
		"containerTpl": "578f8778245977358849a9b5"
	},
	{
		"worldId": "custom_mazuto_00035",
		"containerTpl": "59139c2186f77411564f8e42"
	},
	{
		"worldId": "custom_multiScene_00073",
		"containerTpl": "578f87a3245977356274f2cb"
	},
	{
		"worldId": "custom_multiScene_00055",
		"containerTpl": "578f87a3245977356274f2cb"
	},
	{
		"worldId": "custom_multiScene_00068",
		"containerTpl": "59387ac686f77401442ddd61"
	},
	{
		"worldId": "custom_multiScene_00064",
		"containerTpl": "5909e4b686f7747f5b744fa4"
	},
	{
		"worldId": "custom_multiScene_00072",
		"containerTpl": "578f87ad245977356274f2cc"
	},
	{
		"worldId": "custom_multiScene_00066",
		"containerTpl": "5909d45286f77465a8136dc6"
	},
	{
		"worldId": "custom_multiScene_00069",
		"containerTpl": "578f87ad245977356274f2cc"
	},
	{
		"worldId": "custom_multiScene_00070",
		"containerTpl": "5909d45286f77465a8136dc6"
	},
	{
		"worldId": "custom_multiScene_00071",
		"containerTpl": "578f87a3245977356274f2cb"
	},
	{
		"worldId": "custom_multiScene_00054",
		"containerTpl": "5909d45286f77465a8136dc6"
	},
	{
		"worldId": "custom_multiScene_00076",
		"containerTpl": "578f87a3245977356274f2cb"
	},
	{
		"worldId": "custom_multiScene_00062",
		"containerTpl": "578f87ad245977356274f2cc"
	},
	{
		"worldId": "custom_multiScene_00065",
		"containerTpl": "5909d45286f77465a8136dc6"
	},
	{
		"worldId": "custom_multiScene_00067",
		"containerTpl": "5909d36d86f774660f0bb900"
	},
	{
		"worldId": "custom_multiScene_00074",
		"containerTpl": "5909e4b686f7747f5b744fa4"
	},
	{
		"worldId": "custom_multiScene_00056",
		"containerTpl": "578f87a3245977356274f2cb"
	},
	{
		"worldId": "custom_multiScene_00059",
		"containerTpl": "578f87a3245977356274f2cb"
	},
	{
		"worldId": "custom_multiScene_00060",
		"containerTpl": "578f8778245977358849a9b5"
	},
	{
		"worldId": "custom_multiScene_00061",
		"containerTpl": "578f879c24597735401e6bc6"
	},
	{
		"worldId": "custom_multiScene_00075",
		"containerTpl": "5909d45286f77465a8136dc6"
	},
	{
		"worldId": "custom_multiScene_00057",
		"containerTpl": "578f87ad245977356274f2cc"
	},
	{
		"worldId": "custom_AZS_old_00009",
		"containerTpl": "578f87ad245977356274f2cc"
	},
	{
		"worldId": "custom_AZS_old_00010",
		"containerTpl": "5909d24f86f77466f56e6855"
	},
	{
		"worldId": "custom_Abandoned_Lab_00014",
		"containerTpl": "578f8778245977358849a9b5"
	},
	{
		"worldId": "custom_Abandoned_Lab_00016",
		"containerTpl": "5909e4b686f7747f5b744fa4"
	},
	{
		"worldId": "custom_Abandoned_Lab_00025",
		"containerTpl": "578f87b7245977356274f2cd"
	},
	{
		"worldId": "custom_Abandoned_Lab_00026",
		"containerTpl": "578f87b7245977356274f2cd"
	},
	{
		"worldId": "custom_Abandoned_Lab_00027",
		"containerTpl": "578f87b7245977356274f2cd"
	},
	{
		"worldId": "custom_Abandoned_Lab_00028",
		"containerTpl": "578f87b7245977356274f2cd"
	},
	{
		"worldId": "custom_Abandoned_Lab_00013",
		"containerTpl": "578f8778245977358849a9b5"
	},
	{
		"worldId": "custom_Abandoned_Lab_00012",
		"containerTpl": "5909e4b686f7747f5b744fa4"
	},
	{
		"worldId": "custom_Abandoned_Lab_00017",
		"containerTpl": "578f87b7245977356274f2cd"
	},
	{
		"worldId": "custom_Abandoned_Lab_00018",
		"containerTpl": "578f87b7245977356274f2cd"
	},
	{
		"worldId": "custom_Abandoned_Lab_00019",
		"containerTpl": "578f87b7245977356274f2cd"
	},
	{
		"worldId": "custom_Abandoned_Lab_00020",
		"containerTpl": "578f87b7245977356274f2cd"
	},
	{
		"worldId": "custom_Abandoned_Lab_00021",
		"containerTpl": "578f87b7245977356274f2cd"
	},
	{
		"worldId": "custom_Abandoned_Lab_00022",
		"containerTpl": "578f87b7245977356274f2cd"
	},
	{
		"worldId": "custom_Abandoned_Lab_00023",
		"containerTpl": "578f87b7245977356274f2cd"
	},
	{
		"worldId": "custom_Abandoned_Lab_00024",
		"containerTpl": "578f87b7245977356274f2cd"
	},
	{
		"worldId": "custom_Abandoned_Lab_00015",
		"containerTpl": "578f8778245977358849a9b5"
	},
	{
		"worldId": "Custom_ChemicalFactory_00011",
		"containerTpl": "578f8778245977358849a9b5"
	},
	{
		"worldId": "Custom_Construction_Factory_00004",
		"containerTpl": "5d6fd13186f77424ad2a8c69"
	},
	{
		"worldId": "Custom_Construction_Factory_00001",
		"containerTpl": "5d6fe50986f77449d97f7463"
	},
	{
		"worldId": "Custom_Construction_Factory_00002",
		"containerTpl": "5d6fd45b86f774317075ed43"
	},
	{
		"worldId": "Custom_Construction_Factory_00003",
		"containerTpl": "5d6fe50986f77449d97f7463"
	},
	{
		"worldId": "Custom_Expansion_00006",
		"containerTpl": "5909d5ef86f77467974efbd8"
	},
	{
		"worldId": "Custom_Expansion_00011",
		"containerTpl": "5909e4b686f7747f5b744fa4"
	},
	{
		"worldId": "Custom_Expansion_00012",
		"containerTpl": "5d6fd45b86f774317075ed43"
	},
	{
		"worldId": "Custom_Expansion_00008",
		"containerTpl": "5d6fd45b86f774317075ed43"
	},
	{
		"worldId": "Custom_Expansion_00007",
		"containerTpl": "5d6fd45b86f774317075ed43"
	},
	{
		"worldId": "Custom_Expansion_00010",
		"containerTpl": "5909e4b686f7747f5b744fa4"
	},
	{
		"worldId": "Custom_Expansion_00005",
		"containerTpl": "5d6fd45b86f774317075ed43"
	},
	{
		"worldId": "Custom_Expansion_00009",
		"containerTpl": "578f8778245977358849a9b5"
	},
	{
		"worldId": "custom_Pump_Station_00008",
		"containerTpl": "578f8778245977358849a9b5"
	},
	{
		"worldId": "custom_Pump_Station_00006",
		"containerTpl": "59139c2186f77411564f8e42"
	},
	{
		"worldId": "custom_Pump_Station_00005",
		"containerTpl": "578f8778245977358849a9b5"
	},
	{
		"worldId": "custom_Pump_Station_00007",
		"containerTpl": "59139c2186f77411564f8e42"
	},
	{
		"worldId": "container_shoreline_scripts_00005",
		"containerTpl": "61a89e5445a2672acf66c877"
	},
	{
		"worldId": "container_shoreline_scripts_00002",
		"containerTpl": "61a89e5445a2672acf66c877"
	},
	{
		"worldId": "container_shoreline_scripts_00004",
		"containerTpl": "61a89e5445a2672acf66c877"
	},
	{
		"worldId": "container_shoreline_scripts_00001",
		"containerTpl": "61a89e5445a2672acf66c877"
	},
	{
		"worldId": "container_shoreline_scripts_00003",
		"containerTpl": "61a89e5445a2672acf66c877"
	},
	{
		"worldId": "container_custom_Scripts_00000",
		"containerTpl": "61a89e5445a2672acf66c877"
	}
]