{
  "items": [
    {
      "_id": "63d385d7b3eba6c95d0f0312",
      "_tpl": "5755356824597772cb798962",
      "parentId": "hideout",
      "slotId": "hideout",
      "upd": {
        "UnlimitedCount": true,
        "StackObjectsCount": 1110000
      }
    },
    {
      "_id": "63d385d7b3eba6c95d0f0314",
      "_tpl": "544fb45d4bdc2dee738b4568",
      "parentId": "hideout",
      "slotId": "hideout",
      "upd": {
        "StackObjectsCount": 9642,
        "BuyRestrictionMax": 5,
        "BuyRestrictionCurrent": 0
      }
    },
    {
      "_id": "63d385d7b3eba6c95d0f0316",
      "_tpl": "544fb37f4bdc2dee738b4567",
      "parentId": "hideout",
      "slotId": "hideout",
      "upd": {
        "UnlimitedCount": true,
        "StackObjectsCount": 1110000
      }
    },
    {
      "_id": "63d385d7b3eba6c95d0f0318",
      "_tpl": "574eb85c245977648157eec3",
      "parentId": "hideout",
      "slotId": "hideout",
      "upd": {
        "UnlimitedCount": true,
        "StackObjectsCount": 1110000
      }
    },
    {
      "_id": "63d385d7b3eba6c95d0f031a",
      "_tpl": "5448fee04bdc2dbc018b4567",
      "parentId": "hideout",
      "slotId": "hideout",
      "upd": {
        "StackObjectsCount": 64526,
        "BuyRestrictionMax": 5,
        "BuyRestrictionCurrent": 0
      }
    },
    {
      "_id": "63d385d7b3eba6c95d0f031c",
      "_tpl": "544fb25a4bdc2dfb738b4567",
      "parentId": "hideout",
      "slotId": "hideout",
      "upd": {
        "UnlimitedCount": true,
        "StackObjectsCount": 1110000
      }
    },
    {
      "_id": "63d385d7b3eba6c95d0f031e",
      "_tpl": "544fb3364bdc2d34748b456a",
      "parentId": "hideout",
      "slotId": "hideout",
      "upd": {
        "UnlimitedCount": true,
        "StackObjectsCount": 1110000
      }
    },
    {
      "_id": "63d385d7b3eba6c95d0f0320",
      "_tpl": "590c5d4b86f774784e1b9c45",
      "parentId": "hideout",
      "slotId": "hideout",
      "upd": {
        "StackObjectsCount": 9610,
        "BuyRestrictionMax": 2,
        "BuyRestrictionCurrent": 0
      }
    },
    {
      "_id": "63d385d7b3eba6c95d0f0322",
      "_tpl": "590c661e86f7741e566b646a",
      "parentId": "hideout",
      "slotId": "hideout",
      "upd": {
        "UnlimitedCount": true,
        "StackObjectsCount": 1110000
      }
    },
    {
      "_id": "63d385d7b3eba6c95d0f0324",
      "_tpl": "544fb3f34bdc2d03748b456a",
      "parentId": "hideout",
      "slotId": "hideout",
      "upd": {
        "UnlimitedCount": true,
        "StackObjectsCount": 1110000,
        "BuyRestrictionMax": 4,
        "BuyRestrictionCurrent": 0
      }
    },
    {
      "_id": "63d385d7b3eba6c95d0f0326",
      "_tpl": "590c657e86f77412b013051d",
      "parentId": "hideout",
      "slotId": "hideout",
      "upd": {
        "StackObjectsCount": 6984,
        "BuyRestrictionMax": 3,
        "BuyRestrictionCurrent": 0
      }
    },
    {
      "_id": "63d385d7b3eba6c95d0f0328",
      "_tpl": "590c695186f7741e566b64a2",
      "parentId": "hideout",
      "slotId": "hideout",
      "upd": {
        "StackObjectsCount": 3993,
        "BuyRestrictionMax": 2,
        "BuyRestrictionCurrent": 0
      }
    },
    {
      "_id": "63d385d7b3eba6c95d0f032a",
      "_tpl": "5673de654bdc2d180f8b456d",
      "parentId": "hideout",
      "slotId": "hideout",
      "upd": {
        "StackObjectsCount": 14941,
        "BuyRestrictionMax": 5,
        "BuyRestrictionCurrent": 0
      }
    },
    {
      "_id": "63d385d7b3eba6c95d0f032c",
      "_tpl": "590c678286f77426c9660122",
      "parentId": "hideout",
      "slotId": "hideout",
      "upd": {
        "StackObjectsCount": 19632,
        "BuyRestrictionMax": 3,
        "BuyRestrictionCurrent": 0
      }
    },
    {
      "_id": "63d385d7b3eba6c95d0f032e",
      "_tpl": "5751487e245977207e26a315",
      "parentId": "hideout",
      "slotId": "hideout",
      "upd": {
        "StackObjectsCount": 100,
        "BuyRestrictionMax": 4,
        "BuyRestrictionCurrent": 0
      }
    },
    {
      "_id": "63d385d7b3eba6c95d0f0330",
      "_tpl": "5751a25924597722c463c472",
      "parentId": "hideout",
      "slotId": "hideout",
      "upd": {
        "UnlimitedCount": true,
        "StackObjectsCount": 1110000
      }
    },
    {
      "_id": "63d385d7b3eba6c95d0f0332",
      "_tpl": "590c678286f77426c9660122",
      "parentId": "hideout",
      "slotId": "hideout",
      "upd": {
        "StackObjectsCount": 14885,
        "BuyRestrictionMax": 5,
        "BuyRestrictionCurrent": 0
      }
    },
    {
      "_id": "63d385d7b3eba6c95d0f0334",
      "_tpl": "59fb042886f7746c5005a7b2",
      "parentId": "hideout",
      "slotId": "hideout",
      "upd": {
        "StackObjectsCount": 1847,
        "BuyRestrictionMax": 1,
        "BuyRestrictionCurrent": 0
      }
    },
    {
      "_id": "63d385d7b3eba6c95d0f0336",
      "_tpl": "59fb016586f7746d0d4b423a",
      "parentId": "hideout",
      "slotId": "hideout",
      "upd": {
        "StackObjectsCount": 753,
        "BuyRestrictionMax": 1,
        "BuyRestrictionCurrent": 0
      }
    },
    {
      "_id": "63d385d7b3eba6c95d0f0338",
      "_tpl": "5a8036fb86f77407252ddc02",
      "parentId": "hideout",
      "slotId": "hideout",
      "upd": {
        "UnlimitedCount": true,
        "StackObjectsCount": 1110000
      }
    },
    {
      "_id": "63d385d7b3eba6c95d0f033a",
      "_tpl": "5a80a29286f7742b25692012",
      "parentId": "hideout",
      "slotId": "hideout",
      "upd": {
        "UnlimitedCount": true,
        "StackObjectsCount": 1110000
      }
    },
    {
      "_id": "63d385d7b3eba6c95d0f033c",
      "_tpl": "5aafbcd986f7745e590fff23",
      "parentId": "hideout",
      "slotId": "hideout",
      "upd": {
        "StackObjectsCount": 1950,
        "BuyRestrictionMax": 1,
        "BuyRestrictionCurrent": 0
      }
    },
    {
      "_id": "63d385d7b3eba6c95d0f033e",
      "_tpl": "590c60fc86f77412b13fddcf",
      "parentId": "hideout",
      "slotId": "hideout",
      "upd": {
        "StackObjectsCount": 29539,
        "BuyRestrictionMax": 1,
        "BuyRestrictionCurrent": 0
      }
    },
    {
      "_id": "63d385d7b3eba6c95d0f0340",
      "_tpl": "5780d0532459777a5108b9a2",
      "parentId": "hideout",
      "slotId": "hideout",
      "upd": {
        "StackObjectsCount": 95,
        "BuyRestrictionMax": 1,
        "BuyRestrictionCurrent": 0
      }
    },
    {
      "_id": "63d385d7b3eba6c95d0f0342",
      "_tpl": "590c657e86f77412b013051d",
      "parentId": "hideout",
      "slotId": "hideout",
      "upd": {
        "StackObjectsCount": 14808,
        "BuyRestrictionMax": 2,
        "BuyRestrictionCurrent": 0
      }
    },
    {
      "_id": "63d385d7b3eba6c95d0f0344",
      "_tpl": "5ad5d7d286f77450166e0a89",
      "parentId": "hideout",
      "slotId": "hideout",
      "upd": {
        "StackObjectsCount": 100,
        "BuyRestrictionMax": 1,
        "BuyRestrictionCurrent": 0
      }
    },
    {
      "_id": "63d385d7b3eba6c95d0f0346",
      "_tpl": "567143bf4bdc2d1a0f8b4567",
      "parentId": "hideout",
      "slotId": "hideout",
      "upd": {
        "StackObjectsCount": 758,
        "BuyRestrictionMax": 1,
        "BuyRestrictionCurrent": 0
      }
    },
    {
      "_id": "63d385d7b3eba6c95d0f0348",
      "_tpl": "59fafd4b86f7745ca07e1232",
      "parentId": "hideout",
      "slotId": "hideout",
      "upd": {
        "StackObjectsCount": 873,
        "BuyRestrictionMax": 1,
        "BuyRestrictionCurrent": 0
      }
    },
    {
      "_id": "63d385d7b3eba6c95d0f034a",
      "_tpl": "59fb042886f7746c5005a7b2",
      "parentId": "hideout",
      "slotId": "hideout",
      "upd": {
        "StackObjectsCount": 356,
        "BuyRestrictionMax": 1,
        "BuyRestrictionCurrent": 0
      }
    },
    {
      "_id": "63d385d7b3eba6c95d0f034c",
      "_tpl": "544fb37f4bdc2dee738b4567",
      "parentId": "hideout",
      "slotId": "hideout",
      "upd": {
        "UnlimitedCount": true,
        "StackObjectsCount": 1110000
      }
    },
    {
      "_id": "63d385d7b3eba6c95d0f034e",
      "_tpl": "590c661e86f7741e566b646a",
      "parentId": "hideout",
      "slotId": "hideout",
      "upd": {
        "StackObjectsCount": 2799,
        "BuyRestrictionMax": 5,
        "BuyRestrictionCurrent": 0
      }
    },
    {
      "_id": "63d385d7b3eba6c95d0f0350",
      "_tpl": "5b7c710788a4506dec015957",
      "parentId": "hideout",
      "slotId": "hideout",
      "upd": {
        "StackObjectsCount": 77356,
        "BuyRestrictionMax": 1,
        "BuyRestrictionCurrent": 0
      }
    },
    {
      "_id": "63d385d7b3eba6c95d0f0352",
      "_tpl": "5c0a840b86f7742ffa4f2482",
      "parentId": "hideout",
      "slotId": "hideout",
      "upd": {
        "StackObjectsCount": 253,
        "BuyRestrictionMax": 1,
        "BuyRestrictionCurrent": 0
      }
    },
    {
      "_id": "63d385d7b3eba6c95d0f0354",
      "_tpl": "5c093e3486f77430cb02e593",
      "parentId": "hideout",
      "slotId": "hideout",
      "upd": {
        "StackObjectsCount": 19827,
        "BuyRestrictionMax": 1,
        "BuyRestrictionCurrent": 0
      }
    },
    {
      "_id": "63d385d7b3eba6c95d0f0356",
      "_tpl": "5c10c8fd86f7743d7d706df3",
      "parentId": "hideout",
      "slotId": "hideout",
      "upd": {
        "StackObjectsCount": 19995,
        "BuyRestrictionMax": 3,
        "BuyRestrictionCurrent": 0
      }
    },
    {
      "_id": "63d385d7b3eba6c95d0f0358",
      "_tpl": "5be4038986f774527d3fae60",
      "parentId": "hideout",
      "slotId": "hideout",
      "upd": {
        "UnlimitedCount": true,
        "StackObjectsCount": 1110000
      }
    },
    {
      "_id": "63d385d7b3eba6c95d0f035a",
      "_tpl": "5c94bbff86f7747ee735c08f",
      "parentId": "hideout",
      "slotId": "hideout",
      "upd": {
        "StackObjectsCount": 8886,
        "BuyRestrictionMax": 1,
        "BuyRestrictionCurrent": 0
      }
    },
    {
      "_id": "63d385d7b3eba6c95d0f035c",
      "_tpl": "5c0e533786f7747fa23f4d47",
      "parentId": "hideout",
      "slotId": "hideout",
      "upd": {
        "StackObjectsCount": 2997,
        "BuyRestrictionMax": 3,
        "BuyRestrictionCurrent": 0
      }
    },
    {
      "_id": "63d385d7b3eba6c95d0f035e",
      "_tpl": "5c0e530286f7747fa1419862",
      "parentId": "hideout",
      "slotId": "hideout",
      "upd": {
        "StackObjectsCount": 1964,
        "BuyRestrictionMax": 4,
        "BuyRestrictionCurrent": 0
      }
    },
    {
      "_id": "63d385d7b3eba6c95d0f0360",
      "_tpl": "5af0454c86f7746bf20992e8",
      "parentId": "hideout",
      "slotId": "hideout",
      "upd": {
        "StackObjectsCount": 6841,
        "BuyRestrictionMax": 3,
        "BuyRestrictionCurrent": 0
      }
    },
    {
      "_id": "63d385d7b3eba6c95d0f0362",
      "_tpl": "5c0e531286f7747fa54205c2",
      "parentId": "hideout",
      "slotId": "hideout",
      "upd": {
        "StackObjectsCount": 1992,
        "BuyRestrictionMax": 1,
        "BuyRestrictionCurrent": 0
      }
    },
    {
      "_id": "63d385d7b3eba6c95d0f0364",
      "_tpl": "5aafbcd986f7745e590fff23",
      "parentId": "hideout",
      "slotId": "hideout",
      "upd": {
        "StackObjectsCount": 2566,
        "BuyRestrictionMax": 1,
        "BuyRestrictionCurrent": 0
      }
    },
    {
      "_id": "63d385d7b3eba6c95d0f0366",
      "_tpl": "59e3577886f774176a362503",
      "parentId": "hideout",
      "slotId": "hideout",
      "upd": {
        "StackObjectsCount": 3924,
        "BuyRestrictionMax": 2,
        "BuyRestrictionCurrent": 0
      }
    },
    {
      "_id": "63d385d7b3eba6c95d0f0368",
      "_tpl": "544fb6cc4bdc2d34748b456e",
      "parentId": "hideout",
      "slotId": "hideout",
      "upd": {
        "StackObjectsCount": 3466,
        "BuyRestrictionMax": 5,
        "BuyRestrictionCurrent": 0
      }
    },
    {
      "_id": "63d385d7b3eba6c95d0f036a",
      "_tpl": "5448ff904bdc2d6f028b456e",
      "parentId": "hideout",
      "slotId": "hideout",
      "upd": {
        "StackObjectsCount": 7222,
        "BuyRestrictionMax": 3,
        "BuyRestrictionCurrent": 0
      }
    },
    {
      "_id": "63d385d7b3eba6c95d0f036c",
      "_tpl": "5c0e534186f7747fa1419867",
      "parentId": "hideout",
      "slotId": "hideout",
      "upd": {
        "StackObjectsCount": 1764,
        "BuyRestrictionMax": 1,
        "BuyRestrictionCurrent": 0
      }
    },
    {
      "_id": "63d385d7b3eba6c95d0f036e",
      "_tpl": "5c0a840b86f7742ffa4f2482",
      "parentId": "hideout",
      "slotId": "hideout",
      "upd": {
        "StackObjectsCount": 100,
        "BuyRestrictionMax": 1,
        "BuyRestrictionCurrent": 0
      }
    },
    {
      "_id": "63d385d7b3eba6c95d0f0370",
      "_tpl": "5d80c78786f774403a401e3e",
      "parentId": "hideout",
      "slotId": "hideout",
      "upd": {
        "StackObjectsCount": 50,
        "BuyRestrictionMax": 1,
        "BuyRestrictionCurrent": 0
      }
    },
    {
      "_id": "63d385d7b3eba6c95d0f0372",
      "_tpl": "5af0454c86f7746bf20992e8",
      "parentId": "hideout",
      "slotId": "hideout",
      "upd": {
        "StackObjectsCount": 1970,
        "BuyRestrictionMax": 1,
        "BuyRestrictionCurrent": 0
      }
    },
    {
      "_id": "63d385d7b3eba6c95d0f0374",
      "_tpl": "544fb45d4bdc2dee738b4568",
      "parentId": "hideout",
      "slotId": "hideout",
      "upd": {
        "StackObjectsCount": 38569,
        "BuyRestrictionMax": 2,
        "BuyRestrictionCurrent": 0
      }
    },
    {
      "_id": "63d385d7b3eba6c95d0f0376",
      "_tpl": "5af0548586f7743a532b7e99",
      "parentId": "hideout",
      "slotId": "hideout",
      "upd": {
        "StackObjectsCount": 1931,
        "BuyRestrictionMax": 1,
        "BuyRestrictionCurrent": 0
      }
    },
    {
      "_id": "63d385d7b3eba6c95d0f0378",
      "_tpl": "5c0e531d86f7747fa23f4d42",
      "parentId": "hideout",
      "slotId": "hideout",
      "upd": {
        "StackObjectsCount": 1923,
        "BuyRestrictionMax": 1,
        "BuyRestrictionCurrent": 0
      }
    },
    {
      "_id": "63d385d7b3eba6c95d0f037a",
      "_tpl": "5d1b3a5d86f774252167ba22",
      "parentId": "hideout",
      "slotId": "hideout",
      "upd": {
        "StackObjectsCount": 4992,
        "BuyRestrictionMax": 4,
        "BuyRestrictionCurrent": 0
      }
    },
    {
      "_id": "63d385d7b3eba6c95d0f037c",
      "_tpl": "5d02778e86f774203e7dedbe",
      "parentId": "hideout",
      "slotId": "hideout",
      "upd": {
        "StackObjectsCount": 564,
        "BuyRestrictionMax": 1,
        "BuyRestrictionCurrent": 0
      }
    },
    {
      "_id": "63d385d7b3eba6c95d0f037e",
      "_tpl": "5e4abc6786f77406812bd572",
      "parentId": "hideout",
      "slotId": "hideout",
      "upd": {
        "StackObjectsCount": 1986,
        "BuyRestrictionMax": 1,
        "BuyRestrictionCurrent": 0
      }
    },
    {
      "_id": "63d385d7b3eba6c95d0f0380",
      "_tpl": "59fb042886f7746c5005a7b2",
      "parentId": "hideout",
      "slotId": "hideout",
      "upd": {
        "StackObjectsCount": 282,
        "BuyRestrictionMax": 1,
        "BuyRestrictionCurrent": 0
      }
    },
    {
      "_id": "63d385d7b3eba6c95d0f0382",
      "_tpl": "5b7c710788a4506dec015957",
      "parentId": "hideout",
      "slotId": "hideout",
      "upd": {
        "StackObjectsCount": 173,
        "BuyRestrictionMax": 1,
        "BuyRestrictionCurrent": 0
      }
    },
    {
      "_id": "63d385d7b3eba6c95d0f0384",
      "_tpl": "5c0530ee86f774697952d952",
      "parentId": "hideout",
      "slotId": "hideout",
      "upd": {
        "StackObjectsCount": 199,
        "BuyRestrictionMax": 1,
        "BuyRestrictionCurrent": 0
      }
    },
    {
      "_id": "63d385d7b3eba6c95d0f0386",
      "_tpl": "5a0ee37f86f774023657a86f",
      "parentId": "hideout",
      "slotId": "hideout",
      "upd": {
        "StackObjectsCount": 1998,
        "BuyRestrictionMax": 1,
        "BuyRestrictionCurrent": 0
      }
    },
    {
      "_id": "63d385d8b3eba6c95d0f0388",
      "_tpl": "5e831507ea0a7c419c2f9bd9",
      "parentId": "hideout",
      "slotId": "hideout",
      "upd": {
        "UnlimitedCount": true,
        "StackObjectsCount": 1110000
      }
    },
    {
      "_id": "63d385d8b3eba6c95d0f038a",
      "_tpl": "5e8488fa988a8701445df1e4",
      "parentId": "hideout",
      "slotId": "hideout",
      "upd": {
        "StackObjectsCount": 53346,
        "BuyRestrictionMax": 3,
        "BuyRestrictionCurrent": 0
      }
    },
    {
      "_id": "63d385d8b3eba6c95d0f038c",
      "_tpl": "57347d3d245977448f7b7f61",
      "parentId": "hideout",
      "slotId": "hideout",
      "upd": {
        "StackObjectsCount": 1679,
        "BuyRestrictionMax": 3,
        "BuyRestrictionCurrent": 0
      }
    },
    {
      "_id": "63d385d8b3eba6c95d0f038e",
      "_tpl": "5d1b371186f774253763a656",
      "parentId": "hideout",
      "slotId": "hideout",
      "upd": {
        "StackObjectsCount": 848,
        "BuyRestrictionMax": 1,
        "BuyRestrictionCurrent": 0
      }
    },
    {
      "_id": "63d385d8b3eba6c95d0f0390",
      "_tpl": "5448fee04bdc2dbc018b4567",
      "parentId": "hideout",
      "slotId": "hideout",
      "upd": {
        "StackObjectsCount": 4013,
        "BuyRestrictionMax": 2,
        "BuyRestrictionCurrent": 0
      }
    },
    {
      "_id": "63d385d8b3eba6c95d0f0392",
      "_tpl": "57347d5f245977448b40fa81",
      "parentId": "hideout",
      "slotId": "hideout",
      "upd": {
        "StackObjectsCount": 3906,
        "BuyRestrictionMax": 3,
        "BuyRestrictionCurrent": 0
      }
    },
    {
      "_id": "63d385d8b3eba6c95d0f0394",
      "_tpl": "5c10c8fd86f7743d7d706df3",
      "parentId": "hideout",
      "slotId": "hideout",
      "upd": {
        "StackObjectsCount": 1985,
        "BuyRestrictionMax": 1,
        "BuyRestrictionCurrent": 0
      }
    },
    {
      "_id": "63d385d8b3eba6c95d0f0396",
      "_tpl": "5bc9be8fd4351e00334cae6e",
      "parentId": "hideout",
      "slotId": "hideout",
      "upd": {
        "StackObjectsCount": 4991,
        "BuyRestrictionMax": 2,
        "BuyRestrictionCurrent": 0
      }
    },
    {
      "_id": "63d385d8b3eba6c95d0f0398",
      "_tpl": "5e8488fa988a8701445df1e4",
      "parentId": "hideout",
      "slotId": "hideout",
      "upd": {
        "StackObjectsCount": 2481,
        "BuyRestrictionMax": 2,
        "BuyRestrictionCurrent": 0
      }
    },
    {
      "_id": "63d385d8b3eba6c95d0f039a",
      "_tpl": "593aa4be86f77457f56379f8",
      "parentId": "hideout",
      "slotId": "hideout",
      "upd": {
        "StackObjectsCount": 1998,
        "BuyRestrictionMax": 1,
        "BuyRestrictionCurrent": 0
      }
    },
    {
      "_id": "63d385d8b3eba6c95d0f039c",
      "_tpl": "5938603e86f77435642354f4",
      "parentId": "hideout",
      "slotId": "hideout",
      "upd": {
        "StackObjectsCount": 1984,
        "BuyRestrictionMax": 1,
        "BuyRestrictionCurrent": 0
      }
    },
    {
      "_id": "63d385d8b3eba6c95d0f039e",
      "_tpl": "5780d0532459777a5108b9a2",
      "parentId": "hideout",
      "slotId": "hideout",
      "upd": {
        "StackObjectsCount": 1940,
        "BuyRestrictionMax": 1,
        "BuyRestrictionCurrent": 0
      }
    },
    {
      "_id": "63d385d8b3eba6c95d0f03a0",
      "_tpl": "57347c93245977448d35f6e3",
      "parentId": "hideout",
      "slotId": "hideout",
      "upd": {
        "StackObjectsCount": 4994,
        "BuyRestrictionMax": 2,
        "BuyRestrictionCurrent": 0
      }
    },
    {
      "_id": "63d385d8b3eba6c95d0f03a2",
      "_tpl": "619cbf9e0a7c3a1a2731940a",
      "parentId": "hideout",
      "slotId": "hideout",
      "upd": {
        "StackObjectsCount": 2994,
        "BuyRestrictionMax": 1,
        "BuyRestrictionCurrent": 0
      }
    },
    {
      "_id": "63d385d8b3eba6c95d0f03a4",
      "_tpl": "619cbf7d23893217ec30b689",
      "parentId": "hideout",
      "slotId": "hideout",
      "upd": {
        "StackObjectsCount": 4977,
        "BuyRestrictionMax": 1,
        "BuyRestrictionCurrent": 0
      }
    },
    {
      "_id": "63d385d8b3eba6c95d0f03a6",
      "_tpl": "62a0a043cf4a99369e2624a5",
      "parentId": "hideout",
      "slotId": "hideout",
      "upd": {
        "StackObjectsCount": 19982,
        "BuyRestrictionMax": 5,
        "BuyRestrictionCurrent": 0
      }
    },
    {
      "_id": "63d385d8b3eba6c95d0f03a8",
      "_tpl": "5c0e530286f7747fa1419862",
      "parentId": "hideout",
      "slotId": "hideout",
      "upd": {
        "StackObjectsCount": 1955,
        "BuyRestrictionMax": 3,
        "BuyRestrictionCurrent": 0
      }
    },
    {
      "_id": "63d385d8b3eba6c95d0f03aa",
      "_tpl": "5780cfa52459777dfb276eb1",
      "parentId": "hideout",
      "slotId": "hideout",
      "upd": {
        "StackObjectsCount": 1994,
        "BuyRestrictionMax": 1,
        "BuyRestrictionCurrent": 0
      }
    },
    {
      "_id": "63d385d8b3eba6c95d0f03ac",
      "_tpl": "5448ff904bdc2d6f028b456e",
      "parentId": "hideout",
      "slotId": "hideout",
      "upd": {
        "StackObjectsCount": 19894,
        "BuyRestrictionMax": 5,
        "BuyRestrictionCurrent": 0
      }
    },
    {
      "_id": "63d385d8b3eba6c95d0f03ae",
      "_tpl": "544fb45d4bdc2dee738b4568",
      "parentId": "hideout",
      "slotId": "hideout",
      "upd": {
        "StackObjectsCount": 48798,
        "BuyRestrictionMax": 1,
        "BuyRestrictionCurrent": 0
      }
    }
  ],
  "barter_scheme": {
    "63d385d7b3eba6c95d0f0312": [
      [
        {
          "count": 6638,
          "_tpl": "5449016a4bdc2d6f028b456f"
        }
      ]
    ],
    "63d385d7b3eba6c95d0f0314": [
      [
        {
          "count": 37061,
          "_tpl": "5449016a4bdc2d6f028b456f"
        }
      ]
    ],
    "63d385d7b3eba6c95d0f0316": [
      [
        {
          "count": 8542,
          "_tpl": "5449016a4bdc2d6f028b456f"
        }
      ]
    ],
    "63d385d7b3eba6c95d0f0318": [
      [
        {
          "count": 17896,
          "_tpl": "5449016a4bdc2d6f028b456f"
        }
      ]
    ],
    "63d385d7b3eba6c95d0f031a": [
      [
        {
          "count": 12401,
          "_tpl": "5449016a4bdc2d6f028b456f"
        }
      ]
    ],
    "63d385d7b3eba6c95d0f031c": [
      [
        {
          "count": 2182,
          "_tpl": "5449016a4bdc2d6f028b456f"
        }
      ]
    ],
    "63d385d7b3eba6c95d0f031e": [
      [
        {
          "count": 4283,
          "_tpl": "5449016a4bdc2d6f028b456f"
        }
      ]
    ],
    "63d385d7b3eba6c95d0f0320": [
      [
        {
          "count": 1,
          "_tpl": "5d1b3f2d86f774253763b735"
        }
      ]
    ],
    "63d385d7b3eba6c95d0f0322": [
      [
        {
          "count": 11795,
          "_tpl": "5449016a4bdc2d6f028b456f"
        }
      ]
    ],
    "63d385d7b3eba6c95d0f0324": [
      [
        {
          "count": 42133,
          "_tpl": "5449016a4bdc2d6f028b456f"
        }
      ]
    ],
    "63d385d7b3eba6c95d0f0326": [
      [
        {
          "count": 79739,
          "_tpl": "5449016a4bdc2d6f028b456f"
        }
      ]
    ],
    "63d385d7b3eba6c95d0f0328": [
      [
        {
          "count": 45067,
          "_tpl": "5449016a4bdc2d6f028b456f"
        }
      ]
    ],
    "63d385d7b3eba6c95d0f032a": [
      [
        {
          "count": 1,
          "_tpl": "57347b8b24597737dd42e192"
        },
        {
          "count": 1,
          "_tpl": "56742c284bdc2d98058b456d"
        }
      ]
    ],
    "63d385d7b3eba6c95d0f032c": [
      [
        {
          "count": 1,
          "_tpl": "59e35abd86f7741778269d82"
        }
      ]
    ],
    "63d385d7b3eba6c95d0f032e": [
      [
        {
          "count": 1654,
          "_tpl": "5449016a4bdc2d6f028b456f"
        }
      ]
    ],
    "63d385d7b3eba6c95d0f0330": [
      [
        {
          "count": 2275,
          "_tpl": "5449016a4bdc2d6f028b456f"
        }
      ]
    ],
    "63d385d7b3eba6c95d0f0332": [
      [
        {
          "count": 43524,
          "_tpl": "5449016a4bdc2d6f028b456f"
        }
      ]
    ],
    "63d385d7b3eba6c95d0f0334": [
      [
        {
          "count": 17419.26,
          "_tpl": "569668774bdc2da2298b4568"
        }
      ]
    ],
    "63d385d7b3eba6c95d0f0336": [
      [
        {
          "count": 5,
          "_tpl": "5734758f24597738025ee253"
        },
        {
          "count": 2,
          "_tpl": "59faf7ca86f7740dbe19f6c2"
        },
        {
          "count": 2,
          "_tpl": "5d235a5986f77443f6329bc6"
        }
      ]
    ],
    "63d385d7b3eba6c95d0f0338": [
      [
        {
          "count": 22145,
          "_tpl": "5449016a4bdc2d6f028b456f"
        }
      ]
    ],
    "63d385d7b3eba6c95d0f033a": [
      [
        {
          "count": 10408,
          "_tpl": "5449016a4bdc2d6f028b456f"
        }
      ]
    ],
    "63d385d7b3eba6c95d0f033c": [
      [
        {
          "count": 548610,
          "_tpl": "5449016a4bdc2d6f028b456f"
        }
      ]
    ],
    "63d385d7b3eba6c95d0f033e": [
      [
        {
          "count": 1,
          "_tpl": "59e3658a86f7741776641ac4"
        },
        {
          "count": 1,
          "_tpl": "59e3639286f7741777737013"
        },
        {
          "count": 4,
          "_tpl": "573478bc24597738002c6175"
        }
      ]
    ],
    "63d385d7b3eba6c95d0f0340": [
      [
        {
          "count": 4,
          "_tpl": "5734758f24597738025ee253"
        }
      ]
    ],
    "63d385d7b3eba6c95d0f0342": [
      [
        {
          "count": 1,
          "_tpl": "590a3efd86f77437d351a25b"
        },
        {
          "count": 1,
          "_tpl": "590a3d9c86f774385926e510"
        }
      ]
    ],
    "63d385d7b3eba6c95d0f0344": [
      [
        {
          "count": 60,
          "_tpl": "5734773724597737fd047c14"
        },
        {
          "count": 10,
          "_tpl": "57347d90245977448f7b7f65"
        }
      ]
    ],
    "63d385d7b3eba6c95d0f0346": [
      [
        {
          "count": 6,
          "_tpl": "5d1b3a5d86f774252167ba22"
        },
        {
          "count": 4,
          "_tpl": "5d1b3f2d86f774253763b735"
        }
      ]
    ],
    "63d385d7b3eba6c95d0f0348": [
      [
        {
          "count": 10,
          "_tpl": "59e361e886f774176c10a2a5"
        },
        {
          "count": 10,
          "_tpl": "59e3606886f77417674759a5"
        },
        {
          "count": 10,
          "_tpl": "5e2af02c86f7746d420957d4"
        }
      ]
    ],
    "63d385d7b3eba6c95d0f034a": [
      [
        {
          "count": 20,
          "_tpl": "5af0534a86f7743b6f354284"
        },
        {
          "count": 15,
          "_tpl": "5d1b3a5d86f774252167ba22"
        }
      ]
    ],
    "63d385d7b3eba6c95d0f034c": [
      [
        {
          "count": 1,
          "_tpl": "57347b8b24597737dd42e192"
        }
      ]
    ],
    "63d385d7b3eba6c95d0f034e": [
      [
        {
          "count": 1,
          "_tpl": "57347d5f245977448b40fa81"
        }
      ]
    ],
    "63d385d7b3eba6c95d0f0350": [
      [
        {
          "count": 1106138,
          "_tpl": "5449016a4bdc2d6f028b456f"
        }
      ]
    ],
    "63d385d7b3eba6c95d0f0352": [
      [
        {
          "count": 15,
          "_tpl": "5c052e6986f7746b207bc3c9"
        },
        {
          "count": 15,
          "_tpl": "5c0530ee86f774697952d952"
        },
        {
          "count": 15,
          "_tpl": "5af0548586f7743a532b7e99"
        },
        {
          "count": 15,
          "_tpl": "57347c93245977448d35f6e3"
        }
      ]
    ],
    "63d385d7b3eba6c95d0f0354": [
      [
        {
          "count": 344100,
          "_tpl": "5449016a4bdc2d6f028b456f"
        }
      ]
    ],
    "63d385d7b3eba6c95d0f0356": [
      [
        {
          "count": 40159,
          "_tpl": "5449016a4bdc2d6f028b456f"
        }
      ]
    ],
    "63d385d7b3eba6c95d0f0358": [
      [
        {
          "count": 10157,
          "_tpl": "5449016a4bdc2d6f028b456f"
        }
      ]
    ],
    "63d385d7b3eba6c95d0f035a": [
      [
        {
          "count": 166500,
          "_tpl": "5449016a4bdc2d6f028b456f"
        }
      ]
    ],
    "63d385d7b3eba6c95d0f035c": [
      [
        {
          "count": 46537,
          "_tpl": "5449016a4bdc2d6f028b456f"
        }
      ]
    ],
    "63d385d7b3eba6c95d0f035e": [
      [
        {
          "count": 33897,
          "_tpl": "5449016a4bdc2d6f028b456f"
        }
      ]
    ],
    "63d385d7b3eba6c95d0f0360": [
      [
        {
          "count": 25397,
          "_tpl": "5449016a4bdc2d6f028b456f"
        }
      ]
    ],
    "63d385d7b3eba6c95d0f0362": [
      [
        {
          "count": 1,
          "_tpl": "5d1b3f2d86f774253763b735"
        },
        {
          "count": 1,
          "_tpl": "59e361e886f774176c10a2a5"
        },
        {
          "count": 1,
          "_tpl": "59e35abd86f7741778269d82"
        }
      ]
    ],
    "63d385d7b3eba6c95d0f0364": [
      [
        {
          "count": 7,
          "_tpl": "5b4335ba86f7744d2837a264"
        },
        {
          "count": 7,
          "_tpl": "5d1b3f2d86f774253763b735"
        },
        {
          "count": 2,
          "_tpl": "5755383e24597772cb798966"
        },
        {
          "count": 4,
          "_tpl": "619cc01e0a7c3a1a2731940c"
        }
      ]
    ],
    "63d385d7b3eba6c95d0f0366": [
      [
        {
          "count": 6,
          "_tpl": "5d1b3a5d86f774252167ba22"
        }
      ]
    ],
    "63d385d7b3eba6c95d0f0368": [
      [
        {
          "count": 1,
          "_tpl": "57513fcc24597720a31c09a6"
        }
      ]
    ],
    "63d385d7b3eba6c95d0f036a": [
      [
        {
          "count": 14665,
          "_tpl": "5449016a4bdc2d6f028b456f"
        }
      ]
    ],
    "63d385d7b3eba6c95d0f036c": [
      [
        {
          "count": 4,
          "_tpl": "5d40412b86f7743cb332ac3a"
        }
      ]
    ],
    "63d385d7b3eba6c95d0f036e": [
      [
        {
          "count": 50,
          "_tpl": "5d1b376e86f774252519444e"
        },
        {
          "count": 50,
          "_tpl": "5d40407c86f774318526545a"
        },
        {
          "count": 30,
          "_tpl": "5d403f9186f7743cac3f229b"
        }
      ]
    ],
    "63d385d7b3eba6c95d0f0370": [
      [
        {
          "count": 4,
          "_tpl": "5d1b33a686f7742523398398"
        },
        {
          "count": 4,
          "_tpl": "5d1b385e86f774252167b98a"
        }
      ]
    ],
    "63d385d7b3eba6c95d0f0372": [
      [
        {
          "count": 2,
          "_tpl": "5d1b3f2d86f774253763b735"
        }
      ]
    ],
    "63d385d7b3eba6c95d0f0374": [
      [
        {
          "count": 1,
          "_tpl": "60098b1705871270cd5352a1"
        }
      ]
    ],
    "63d385d7b3eba6c95d0f0376": [
      [
        {
          "count": 1,
          "_tpl": "5b4335ba86f7744d2837a264"
        },
        {
          "count": 3,
          "_tpl": "5d1b3a5d86f774252167ba22"
        }
      ]
    ],
    "63d385d7b3eba6c95d0f0378": [
      [
        {
          "count": 2,
          "_tpl": "59e3606886f77417674759a5"
        },
        {
          "count": 1,
          "_tpl": "59e361e886f774176c10a2a5"
        }
      ]
    ],
    "63d385d7b3eba6c95d0f037a": [
      [
        {
          "count": 3,
          "_tpl": "56742c284bdc2d98058b456d"
        },
        {
          "count": 2,
          "_tpl": "57347b8b24597737dd42e192"
        }
      ]
    ],
    "63d385d7b3eba6c95d0f037c": [
      [
        {
          "count": 2,
          "_tpl": "5e2aef7986f7746d3f3c33f5"
        }
      ]
    ],
    "63d385d7b3eba6c95d0f037e": [
      [
        {
          "count": 2,
          "_tpl": "590c695186f7741e566b64a2"
        },
        {
          "count": 2,
          "_tpl": "5755383e24597772cb798966"
        },
        {
          "count": 2,
          "_tpl": "5d02797c86f774203f38e30a"
        },
        {
          "count": 3,
          "_tpl": "5d1b3a5d86f774252167ba22"
        }
      ]
    ],
    "63d385d7b3eba6c95d0f0380": [
      [
        {
          "count": 150,
          "level": 17,
          "side": "Any",
          "_tpl": "59f32c3b86f77472a31742f0"
        }
      ]
    ],
    "63d385d7b3eba6c95d0f0382": [
      [
        {
          "count": 100,
          "level": 10,
          "side": "Any",
          "_tpl": "59f32c3b86f77472a31742f0"
        }
      ]
    ],
    "63d385d7b3eba6c95d0f0384": [
      [
        {
          "count": 20,
          "level": 39,
          "side": "Any",
          "_tpl": "59f32c3b86f77472a31742f0"
        },
        {
          "count": 140,
          "level": 10,
          "side": "Usec",
          "_tpl": "59f32c3b86f77472a31742f0"
        }
      ]
    ],
    "63d385d7b3eba6c95d0f0386": [
      [
        {
          "count": 8,
          "_tpl": "5e2af02c86f7746d420957d4"
        }
      ]
    ],
    "63d385d8b3eba6c95d0f0388": [
      [
        {
          "count": 4263,
          "_tpl": "5449016a4bdc2d6f028b456f"
        }
      ]
    ],
    "63d385d8b3eba6c95d0f038a": [
      [
        {
          "count": 13949,
          "_tpl": "5449016a4bdc2d6f028b456f"
        }
      ]
    ],
    "63d385d8b3eba6c95d0f038c": [
      [
        {
          "count": 1,
          "_tpl": "5751487e245977207e26a315"
        }
      ]
    ],
    "63d385d8b3eba6c95d0f038e": [
      [
        {
          "count": 4,
          "_tpl": "6389c6463485cf0eeb260715"
        }
      ]
    ],
    "63d385d8b3eba6c95d0f0390": [
      [
        {
          "count": 1,
          "_tpl": "59e361e886f774176c10a2a5"
        }
      ]
    ],
    "63d385d8b3eba6c95d0f0392": [
      [
        {
          "count": 2,
          "_tpl": "57347c93245977448d35f6e3"
        }
      ]
    ],
    "63d385d8b3eba6c95d0f0394": [
      [
        {
          "count": 1,
          "_tpl": "5d1b3f2d86f774253763b735"
        },
        {
          "count": 1,
          "_tpl": "590a3d9c86f774385926e510"
        }
      ]
    ],
    "63d385d8b3eba6c95d0f0396": [
      [
        {
          "count": 4,
          "_tpl": "575062b524597720a31c09a1"
        }
      ]
    ],
    "63d385d8b3eba6c95d0f0398": [
      [
        {
          "count": 2,
          "_tpl": "59e35ef086f7741777737012"
        }
      ]
    ],
    "63d385d8b3eba6c95d0f039a": [
      [
        {
          "count": 7,
          "_tpl": "57347cd0245977445a2d6ff1"
        },
        {
          "count": 3,
          "_tpl": "5734795124597738002c6176"
        }
      ]
    ],
    "63d385d8b3eba6c95d0f039c": [
      [
        {
          "count": 7,
          "_tpl": "5d1b3a5d86f774252167ba22"
        }
      ]
    ],
    "63d385d8b3eba6c95d0f039e": [
      [
        {
          "count": 2,
          "_tpl": "575062b524597720a31c09a1"
        },
        {
          "count": 4,
          "_tpl": "5448ff904bdc2d6f028b456e"
        },
        {
          "count": 2,
          "_tpl": "57347d8724597744596b4e76"
        }
      ]
    ],
    "63d385d8b3eba6c95d0f03a0": [
      [
        {
          "count": 2,
          "_tpl": "5d4041f086f7743cac3f22a7"
        }
      ]
    ],
    "63d385d8b3eba6c95d0f03a2": [
      [
        {
          "count": 508883,
          "_tpl": "5449016a4bdc2d6f028b456f"
        }
      ]
    ],
    "63d385d8b3eba6c95d0f03a4": [
      [
        {
          "count": 20,
          "_tpl": "619cc01e0a7c3a1a2731940c"
        },
        {
          "count": 15,
          "_tpl": "5d1b3f2d86f774253763b735"
        },
        {
          "count": 12,
          "_tpl": "59e361e886f774176c10a2a5"
        }
      ]
    ],
    "63d385d8b3eba6c95d0f03a6": [
      [
        {
          "count": 1,
          "_tpl": "573476d324597737da2adc13"
        },
        {
          "count": 1,
          "_tpl": "5734770f24597738025ee254"
        },
        {
          "count": 1,
          "_tpl": "573476f124597737e04bf328"
        },
        {
          "count": 1,
          "_tpl": "573475fb24597737fb1379e1"
        }
      ]
    ],
    "63d385d8b3eba6c95d0f03a8": [
      [
        {
          "count": 2,
          "_tpl": "62a0a043cf4a99369e2624a5"
        }
      ]
    ],
    "63d385d8b3eba6c95d0f03aa": [
      [
        {
          "count": 1,
          "_tpl": "6389c6463485cf0eeb260715"
        },
        {
          "count": 1,
          "_tpl": "6389c6c7dbfd5e4b95197e68"
        },
        {
          "count": 5,
          "_tpl": "5d1b3a5d86f774252167ba22"
        }
      ]
    ],
    "63d385d8b3eba6c95d0f03ac": [
      [
        {
          "count": 1,
          "_tpl": "5d1b3a5d86f774252167ba22"
        }
      ]
    ],
    "63d385d8b3eba6c95d0f03ae": [
      [
        {
          "count": 1,
          "_tpl": "59e3596386f774176c10a2a2"
        }
      ]
    ]
  },
  "loyal_level_items": {
    "63d385d7b3eba6c95d0f0312": 1,
    "63d385d7b3eba6c95d0f0314": 2,
    "63d385d7b3eba6c95d0f0316": 1,
    "63d385d7b3eba6c95d0f0318": 1,
    "63d385d7b3eba6c95d0f031a": 1,
    "63d385d7b3eba6c95d0f031c": 1,
    "63d385d7b3eba6c95d0f031e": 1,
    "63d385d7b3eba6c95d0f0320": 1,
    "63d385d7b3eba6c95d0f0322": 1,
    "63d385d7b3eba6c95d0f0324": 4,
    "63d385d7b3eba6c95d0f0326": 4,
    "63d385d7b3eba6c95d0f0328": 4,
    "63d385d7b3eba6c95d0f032a": 1,
    "63d385d7b3eba6c95d0f032c": 2,
    "63d385d7b3eba6c95d0f032e": 2,
    "63d385d7b3eba6c95d0f0330": 2,
    "63d385d7b3eba6c95d0f0332": 3,
    "63d385d7b3eba6c95d0f0334": 3,
    "63d385d7b3eba6c95d0f0336": 4,
    "63d385d7b3eba6c95d0f0338": 1,
    "63d385d7b3eba6c95d0f033a": 1,
    "63d385d7b3eba6c95d0f033c": 3,
    "63d385d7b3eba6c95d0f033e": 2,
    "63d385d7b3eba6c95d0f0340": 2,
    "63d385d7b3eba6c95d0f0342": 2,
    "63d385d7b3eba6c95d0f0344": 4,
    "63d385d7b3eba6c95d0f0346": 2,
    "63d385d7b3eba6c95d0f0348": 2,
    "63d385d7b3eba6c95d0f034a": 3,
    "63d385d7b3eba6c95d0f034c": 1,
    "63d385d7b3eba6c95d0f034e": 1,
    "63d385d7b3eba6c95d0f0350": 1,
    "63d385d7b3eba6c95d0f0352": 4,
    "63d385d7b3eba6c95d0f0354": 1,
    "63d385d7b3eba6c95d0f0356": 4,
    "63d385d7b3eba6c95d0f0358": 2,
    "63d385d7b3eba6c95d0f035a": 4,
    "63d385d7b3eba6c95d0f035c": 4,
    "63d385d7b3eba6c95d0f035e": 4,
    "63d385d7b3eba6c95d0f0360": 3,
    "63d385d7b3eba6c95d0f0362": 3,
    "63d385d7b3eba6c95d0f0364": 2,
    "63d385d7b3eba6c95d0f0366": 4,
    "63d385d7b3eba6c95d0f0368": 1,
    "63d385d7b3eba6c95d0f036a": 1,
    "63d385d7b3eba6c95d0f036c": 3,
    "63d385d7b3eba6c95d0f036e": 4,
    "63d385d7b3eba6c95d0f0370": 3,
    "63d385d7b3eba6c95d0f0372": 2,
    "63d385d7b3eba6c95d0f0374": 1,
    "63d385d7b3eba6c95d0f0376": 4,
    "63d385d7b3eba6c95d0f0378": 4,
    "63d385d7b3eba6c95d0f037a": 1,
    "63d385d7b3eba6c95d0f037c": 2,
    "63d385d7b3eba6c95d0f037e": 3,
    "63d385d7b3eba6c95d0f0380": 3,
    "63d385d7b3eba6c95d0f0382": 2,
    "63d385d7b3eba6c95d0f0384": 3,
    "63d385d7b3eba6c95d0f0386": 2,
    "63d385d8b3eba6c95d0f0388": 1,
    "63d385d8b3eba6c95d0f038a": 3,
    "63d385d8b3eba6c95d0f038c": 2,
    "63d385d8b3eba6c95d0f038e": 2,
    "63d385d8b3eba6c95d0f0390": 1,
    "63d385d8b3eba6c95d0f0392": 1,
    "63d385d8b3eba6c95d0f0394": 2,
    "63d385d8b3eba6c95d0f0396": 2,
    "63d385d8b3eba6c95d0f0398": 1,
    "63d385d8b3eba6c95d0f039a": 1,
    "63d385d8b3eba6c95d0f039c": 1,
    "63d385d8b3eba6c95d0f039e": 1,
    "63d385d8b3eba6c95d0f03a0": 1,
    "63d385d8b3eba6c95d0f03a2": 3,
    "63d385d8b3eba6c95d0f03a4": 4,
    "63d385d8b3eba6c95d0f03a6": 1,
    "63d385d8b3eba6c95d0f03a8": 3,
    "63d385d8b3eba6c95d0f03aa": 2,
    "63d385d8b3eba6c95d0f03ac": 1,
    "63d385d8b3eba6c95d0f03ae": 1
  }
}